[
    {
        "id": 134,
        "version": 0,
        "name": "Middle La Noscea",
        "name_fr": "Noscea centrale",
        "name_ja": "中央ラノシア",
        "name_de": "Zentrales La Noscea",
        "size_factor": 100,
        "map": 15,
        "aetherytes": [
            {
                "type": 60453,
                "x": 26.1,
                "y": 16.4,
                "name": "Summerford Farms",
                "name_fr": "Vergers d'Estival",
                "name_ja": "サマーフォード庄",
                "name_de": "Sommerfurt-Höfe"
            }
        ],
        "mobs": [
            {
                "id": 29,
                "name": "Vogaal ja",
                "name_fr": "Vogaal ja",
                "name_ja": "醜男のヴォガージャ",
                "name_de": "Vogaal ja",
                "rank": 2,
                "npcbase": 3201,
                "mob_index": 1
            }
        ]
    },
    {
        "id": 135,
        "version": 0,
        "name": "Lower La Noscea",
        "name_fr": "Basse-Noscea",
        "name_ja": "低地ラノシア",
        "name_de": "Unteres La Noscea",
        "size_factor": 100,
        "map": 16,
        "aetherytes": [
            {
                "type": 60453,
                "x": 24.6,
                "y": 35.0,
                "name": "Moraby Drydocks",
                "name_fr": "Chantier naval de Moraby",
                "name_ja": "モラビー造船廠",
                "name_de": "Moraby-Trockendocks"
            }
        ],
        "mobs": [
            {
                "id": 32,
                "name": "Unktehi",
                "name_fr": "Unktehi",
                "name_ja": "ウンクテヒ",
                "name_de": "Unktehi",
                "rank": 2,
                "npcbase": 3202,
                "mob_index": 1
            }
        ]
    },
    {
        "id": 137,
        "version": 0,
        "name": "Eastern La Noscea",
        "name_fr": "Noscea orientale",
        "name_ja": "東ラノシア",
        "name_de": "Östliches La Noscea",
        "size_factor": 100,
        "map": 17,
        "aetherytes": [
            {
                "type": 60453,
                "x": 31.3,
                "y": 30.8,
                "name": "Costa del Sol",
                "name_fr": "Costa del Sol",
                "name_ja": "コスタ・デル・ソル",
                "name_de": "Sonnenküste"
            },
            {
                "type": 60453,
                "x": 21.1,
                "y": 21.6,
                "name": "Wineport",
                "name_fr": "Port-aux-Vins",
                "name_ja": "ワインポート",
                "name_de": "Weinhafen"
            }
        ],
        "mobs": [
            {
                "id": 35,
                "name": "Hellsclaw",
                "name_fr": "Griffe des enfers magitek",
                "name_ja": "魔導ヘルズクロー",
                "name_de": "Höllenklaue",
                "rank": 2,
                "npcbase": 3203,
                "mob_index": 1
            }
        ]
    },
    {
        "id": 138,
        "version": 0,
        "name": "Western La Noscea",
        "name_fr": "Noscea occidentale",
        "name_ja": "西ラノシア",
        "name_de": "Westliches La Noscea",
        "size_factor": 100,
        "map": 18,
        "aetherytes": [
            {
                "type": 60453,
                "x": 34.6,
                "y": 31.8,
                "name": "Swiftperch",
                "name_fr": "Le Martinet",
                "name_ja": "スウィフトパーチ入植地",
                "name_de": "Tölpelturm-Siedlung"
            },
            {
                "type": 60453,
                "x": 26.7,
                "y": 25.9,
                "name": "Aleport",
                "name_fr": "Port-aux-Ales",
                "name_ja": "エールポート",
                "name_de": "Bierhafen"
            }
        ],
        "mobs": [
            {
                "id": 38,
                "name": "Nahn",
                "name_fr": "Nahn",
                "name_ja": "ナン",
                "name_de": "Nahn",
                "rank": 2,
                "npcbase": 3204,
                "mob_index": 1
            }
        ]
    },
    {
        "id": 139,
        "version": 0,
        "name": "Upper La Noscea",
        "name_fr": "Haute-Noscea",
        "name_ja": "高地ラノシア",
        "name_de": "Oberes La Noscea",
        "size_factor": 100,
        "map": 19,
        "aetherytes": [
            {
                "type": 60453,
                "x": 30.3,
                "y": 23.4,
                "name": "Camp Bronze Lake",
                "name_fr": "Camp du lac d'Airain",
                "name_ja": "キャンプ・ブロンズレイク",
                "name_de": "Camp Bronzesee"
            }
        ],
        "mobs": [
            {
                "id": 41,
                "name": "Marberry",
                "name_fr": "Marberry",
                "name_ja": "マーベリー",
                "name_de": "Marberry",
                "rank": 2,
                "npcbase": 3205,
                "mob_index": 1
            }
        ]
    },
    {
        "id": 180,
        "version": 0,
        "name": "Outer La Noscea",
        "name_fr": "Noscea extérieure",
        "name_ja": "外地ラノシア",
        "name_de": "Äußeres La Noscea",
        "size_factor": 100,
        "map": 30,
        "aetherytes": [
            {
                "type": 60453,
                "x": 19.2,
                "y": 17.2,
                "name": "Camp Overlook",
                "name_fr": "Camp du Guet",
                "name_ja": "キャンプ・オーバールック",
                "name_de": "Camp Ausblick"
            }
        ],
        "mobs": [
            {
                "id": 44,
                "name": "Cornu",
                "name_fr": "Cornu",
                "name_ja": "コンヌ",
                "name_de": "Cornu",
                "rank": 2,
                "npcbase": 3206,
                "mob_index": 1
            }
        ]
    },
    {
        "id": 148,
        "version": 0,
        "name": "Central Shroud",
        "name_fr": "Forêt centrale",
        "name_ja": "黒衣森：中央森林",
        "name_de": "Tiefer Wald",
        "size_factor": 100,
        "map": 4,
        "aetherytes": [
            {
                "type": 60453,
                "x": 21.8,
                "y": 22.2,
                "name": "Bentbranch Meadows",
                "name_fr": "Ranch de Brancharquée",
                "name_ja": "ベントブランチ牧場",
                "name_de": "Gut Zwieselgrund"
            }
        ],
        "mobs": [
            {
                "id": 2,
                "name": "Forneus",
                "name_fr": "Forneus",
                "name_ja": "ファルネウス",
                "name_de": "Forneus",
                "rank": 2,
                "npcbase": 3192,
                "mob_index": 1
            }
        ]
    },
    {
        "id": 152,
        "version": 0,
        "name": "East Shroud",
        "name_fr": "Forêt de l'est",
        "name_ja": "黒衣森：東部森林",
        "name_de": "Ostwald",
        "size_factor": 100,
        "map": 5,
        "aetherytes": [
            {
                "type": 60453,
                "x": 17.8,
                "y": 27.5,
                "name": "The Hawthorne Hut",
                "name_fr": "Hutte des Hawthorne",
                "name_ja": "ホウソーン家の山塞",
                "name_de": "Jagdhütte der Hawthornes"
            }
        ],
        "mobs": [
            {
                "id": 5,
                "name": "Melt",
                "name_fr": "Fondu",
                "name_ja": "メルティゼリー",
                "name_de": "Schmelze",
                "rank": 2,
                "npcbase": 3193,
                "mob_index": 1
            }
        ]
    },
    {
        "id": 153,
        "version": 0,
        "name": "South Shroud",
        "name_fr": "Forêt du sud",
        "name_ja": "黒衣森：南部森林",
        "name_de": "Südwald",
        "size_factor": 100,
        "map": 6,
        "aetherytes": [
            {
                "type": 60453,
                "x": 16.9,
                "y": 28.6,
                "name": "Camp Tranquil",
                "name_fr": "Camp des Sentes tranquilles",
                "name_ja": "キャンプ・トランキル",
                "name_de": "Camp Seelenruhe"
            },
            {
                "type": 60453,
                "x": 25.1,
                "y": 20.1,
                "name": "Quarrymill",
                "name_fr": "Moulin de la Carrière",
                "name_ja": "クォーリーミル",
                "name_de": "Mühlenbruch"
            }
        ],
        "mobs": [
            {
                "id": 8,
                "name": "Ghede ti malice",
                "name_fr": "Guédé ti-malice",
                "name_ja": "ゲーデ",
                "name_de": "Ghede titus häme",
                "rank": 2,
                "npcbase": 3194,
                "mob_index": 1
            }
        ]
    },
    {
        "id": 154,
        "version": 0,
        "name": "North Shroud",
        "name_fr": "Forêt du nord",
        "name_ja": "黒衣森：北部森林",
        "name_de": "Nordwald",
        "size_factor": 100,
        "map": 7,
        "aetherytes": [
            {
                "type": 60453,
                "x": 20.6,
                "y": 26.1,
                "name": "Fallgourd Float",
                "name_fr": "Radeau de la Calebasse",
                "name_ja": "フォールゴウド",
                "name_de": "Herbstkürbis-See"
            }
        ],
        "mobs": [
            {
                "id": 11,
                "name": "Girtab",
                "name_fr": "Girtab",
                "name_ja": "ギルタブ",
                "name_de": "Girtab",
                "rank": 2,
                "npcbase": 3195,
                "mob_index": 1
            }
        ]
    },
    {
        "id": 140,
        "version": 0,
        "name": "Western Thanalan",
        "name_fr": "Thanalan occidental",
        "name_ja": "西ザナラーン",
        "name_de": "Westliches Thanalan",
        "size_factor": 100,
        "map": 20,
        "aetherytes": [
            {
                "type": 60453,
                "x": 22.9,
                "y": 16.9,
                "name": "Horizon",
                "name_fr": "Horizon",
                "name_ja": "ホライズン",
                "name_de": "Horizont"
            }
        ],
        "mobs": [
            {
                "id": 14,
                "name": "Alectryon",
                "name_fr": "Alectryon",
                "name_ja": "アレクトリオン",
                "name_de": "Alectryon",
                "rank": 2,
                "npcbase": 3196,
                "mob_index": 1
            }
        ]
    },
    {
        "id": 141,
        "version": 0,
        "name": "Central Thanalan",
        "name_fr": "Thanalan central",
        "name_ja": "中央ザナラーン",
        "name_de": "Zentrales Thanalan",
        "size_factor": 100,
        "map": 21,
        "aetherytes": [
            {
                "type": 60453,
                "x": 21.1,
                "y": 18.2,
                "name": "Black Brush Station",
                "name_fr": "Gare de Roncenoire",
                "name_ja": "ブラックブラッシュ停留所",
                "name_de": "Kohlenstaub-Bahnhof"
            }
        ],
        "mobs": [
            {
                "id": 17,
                "name": "Sabotender bailarina",
                "name_fr": "Pampa ballerine",
                "name_ja": "サボテンダー・バイラリーナ",
                "name_de": "Sabotender bailarina",
                "rank": 2,
                "npcbase": 3197,
                "mob_index": 1
            }
        ]
    },
    {
        "id": 145,
        "version": 0,
        "name": "Eastern Thanalan",
        "name_fr": "Thanalan oriental",
        "name_ja": "東ザナラーン",
        "name_de": "Östliches Thanalan",
        "size_factor": 100,
        "map": 22,
        "aetherytes": [
            {
                "type": 60453,
                "x": 13.8,
                "y": 24.3,
                "name": "Camp Drybone",
                "name_fr": "Camp des Os desséchés",
                "name_ja": "キャンプ・ドライボーン",
                "name_de": "Camp Knochenbleich"
            }
        ],
        "mobs": [
            {
                "id": 20,
                "name": "Maahes",
                "name_fr": "Maahes",
                "name_ja": "マヘス",
                "name_de": "Maahes",
                "rank": 2,
                "npcbase": 3198,
                "mob_index": 1
            }
        ]
    },
    {
        "id": 146,
        "version": 0,
        "name": "Southern Thanalan",
        "name_fr": "Thanalan méridional",
        "name_ja": "南ザナラーン",
        "name_de": "Südliches Thanalan",
        "size_factor": 100,
        "map": 23,
        "aetherytes": [
            {
                "type": 60453,
                "x": 18.3,
                "y": 13.2,
                "name": "Little Ala Mhigo",
                "name_fr": "Petite Ala Mhigo",
                "name_ja": "リトルアラミゴ",
                "name_de": "Klein-Ala Mhigo"
            },
            {
                "type": 60453,
                "x": 15.0,
                "y": 29.6,
                "name": "Forgotten Springs",
                "name_fr": "Oasis oubliée",
                "name_ja": "忘れられたオアシス",
                "name_de": "Die Vergessene Oase"
            }
        ],
        "mobs": [
            {
                "id": 23,
                "name": "Zanig'oh",
                "name_fr": "Zanig'oh",
                "name_ja": "ザニゴ",
                "name_de": "Zanig'oh",
                "rank": 2,
                "npcbase": 3199,
                "mob_index": 1
            }
        ]
    },
    {
        "id": 147,
        "version": 0,
        "name": "Northern Thanalan",
        "name_fr": "Thanalan septentrional",
        "name_ja": "北ザナラーン",
        "name_de": "Nördliches Thanalan",
        "size_factor": 100,
        "map": 24,
        "aetherytes": [
            {
                "type": 60453,
                "x": 21.9,
                "y": 30.6,
                "name": "Camp Bluefog",
                "name_fr": "Camp de Brumebleue",
                "name_ja": "キャンプ・ブルーフォグ",
                "name_de": "Camp Blauer Dunst"
            },
            {
                "type": 60453,
                "x": 21.0,
                "y": 20.9,
                "name": "Ceruleum Processing Plant",
                "name_fr": "Usine de céruleum",
                "name_ja": "青燐精製所",
                "name_de": "Erdseim-Fabrik"
            }
        ],
        "mobs": [
            {
                "id": 26,
                "name": "Dalvag's final flame",
                "name_fr": "Dernière flamme de dalvag",
                "name_ja": "ファイナルフレイム",
                "name_de": "Letzte flamme dalvags",
                "rank": 2,
                "npcbase": 3200,
                "mob_index": 1
            }
        ]
    },
    {
        "id": 155,
        "version": 0,
        "name": "Coerthas Central Highlands",
        "name_fr": "Hautes terres du Coerthas central",
        "name_ja": "クルザス中央高地",
        "name_de": "Zentrales Hochland von Coerthas",
        "size_factor": 100,
        "map": 53,
        "aetherytes": [
            {
                "type": 60453,
                "x": 26.0,
                "y": 16.8,
                "name": "Camp Dragonhead",
                "name_fr": "Camp de la Tête du dragon",
                "name_ja": "キャンプ・ドラゴンヘッド",
                "name_de": "Camp Drachenkopf"
            }
        ],
        "mobs": [
            {
                "id": 47,
                "name": "Marraco",
                "name_fr": "Marraco",
                "name_ja": "マラク",
                "name_de": "Marraco",
                "rank": 2,
                "npcbase": 3207,
                "mob_index": 1
            }
        ]
    },
    {
        "id": 397,
        "version": 1,
        "name": "Coerthas Western Highlands",
        "name_fr": "Hautes terres du Coerthas occidental",
        "name_ja": "クルザス西部高地",
        "name_de": "Westliches Hochland von Coerthas",
        "size_factor": 95,
        "map": 211,
        "aetherytes": [
            {
                "type": 60453,
                "x": 32.1,
                "y": 36.8,
                "name": "Falcon's Nest",
                "name_fr": "Nid du faucon",
                "name_ja": "ファルコンネスト",
                "name_de": "Falkenhorst"
            }
        ],
        "mobs": [
            {
                "id": 54,
                "name": "Mirka",
                "name_fr": "Mirka",
                "name_ja": "ミルカ",
                "name_de": "Mirka",
                "rank": 2,
                "npcbase": 4539,
                "mob_index": 1
            },
            {
                "id": 55,
                "name": "Lyuba",
                "name_fr": "Lyuba",
                "name_ja": "リューバ",
                "name_de": "Lyuba",
                "rank": 2,
                "npcbase": 4540,
                "mob_index": 2
            }
        ]
    },
    {
        "id": 156,
        "version": 0,
        "name": "Mor Dhona",
        "name_fr": "Mor Dhona",
        "name_ja": "モードゥナ",
        "name_de": "Mor Dhona",
        "size_factor": 100,
        "map": 25,
        "aetherytes": [
            {
                "type": 60453,
                "x": 22.3,
                "y": 8.1,
                "name": "Revenant's Toll",
                "name_fr": "Glas des revenants",
                "name_ja": "レヴナンツトール",
                "name_de": "Geisterzoll"
            }
        ],
        "mobs": [
            {
                "id": 50,
                "name": "Kurrea",
                "name_fr": "Kurrea",
                "name_ja": "クーレア",
                "name_de": "Kurrea",
                "rank": 2,
                "npcbase": 3208,
                "mob_index": 1
            }
        ]
    },
    {
        "id": 401,
        "version": 1,
        "name": "The Sea of Clouds",
        "name_fr": "L'Écume des cieux d'Abalathia",
        "name_ja": "アバラシア雲海",
        "name_de": "Abalathisches Wolkenmeer",
        "size_factor": 95,
        "map": 215,
        "aetherytes": [
            {
                "type": 60453,
                "x": 10.5,
                "y": 14.2,
                "name": "Ok' Zundu",
                "name_fr": "Ok' Zundu",
                "name_ja": "オク・ズンド",
                "name_de": "Ok' Zundo"
            },
            {
                "type": 60453,
                "x": 10.3,
                "y": 33.6,
                "name": "Camp Cloudtop",
                "name_fr": "Camp de Cime-des-nuages",
                "name_ja": "キャンプ・クラウドトップ",
                "name_de": "Camp Wolkenwipfel"
            }
        ],
        "mobs": [
            {
                "id": 74,
                "name": "Enkelados",
                "name_fr": "Enkélados",
                "name_ja": "エンケドラス",
                "name_de": "Engedoras",
                "rank": 2,
                "npcbase": 4547,
                "mob_index": 1
            },
            {
                "id": 75,
                "name": "Sisiutl",
                "name_fr": "Sisiutl",
                "name_ja": "シシウトゥル",
                "name_de": "Sisiutl",
                "rank": 2,
                "npcbase": 4548,
                "mob_index": 2
            }
        ]
    },
    {
        "id": 402,
        "version": 1,
        "name": "Azys Lla",
        "name_fr": "Azys Lla",
        "name_ja": "アジス・ラー",
        "name_de": "Azys Lla",
        "size_factor": 95,
        "map": 216,
        "aetherytes": [
            {
                "type": 60453,
                "x": 8.1,
                "y": 10.6,
                "name": "Helix",
                "name_fr": "Hélice",
                "name_ja": "ポート・ヘリックス",
                "name_de": "Helix"
            }
        ],
        "mobs": [
            {
                "id": 79,
                "name": "Campacti",
                "name_fr": "Campacti",
                "name_ja": "キャムパクティ",
                "name_de": "Campacti",
                "rank": 2,
                "npcbase": 4549,
                "mob_index": 1
            },
            {
                "id": 80,
                "name": "Stench blossom",
                "name_fr": "Fleur nauséabonde",
                "name_ja": "センチブロッサム",
                "name_de": "Pestwurz",
                "rank": 2,
                "npcbase": 4550,
                "mob_index": 2
            }
        ]
    },
    {
        "id": 398,
        "version": 1,
        "name": "The Dravanian Forelands",
        "name_fr": "Avant-pays dravanien",
        "name_ja": "高地ドラヴァニア",
        "name_de": "Dravanisches Vorland",
        "size_factor": 95,
        "map": 212,
        "aetherytes": [
            {
                "type": 60453,
                "x": 33.2,
                "y": 23.2,
                "name": "Tailfeather",
                "name_fr": "La Penne",
                "name_ja": "テイルフェザー",
                "name_de": "Fiederhag"
            },
            {
                "type": 60453,
                "x": 16.5,
                "y": 23.3,
                "name": "Anyx Trine",
                "name_fr": "Annexe Trine",
                "name_ja": "不浄の三塔",
                "name_de": "Trinär-Annex"
            }
        ],
        "mobs": [
            {
                "id": 59,
                "name": "Pylraster",
                "name_fr": "Pirlasta",
                "name_ja": "パイルラスタ",
                "name_de": "Xhauron",
                "rank": 2,
                "npcbase": 4541,
                "mob_index": 1
            },
            {
                "id": 60,
                "name": "Lord of the wyverns",
                "name_fr": "Seigneur des wyvernes",
                "name_ja": "ワイバーンロード",
                "name_de": "Wyvern-lord",
                "rank": 2,
                "npcbase": 4542,
                "mob_index": 2
            }
        ]
    },
    {
        "id": 399,
        "version": 1,
        "name": "The Dravanian Hinterlands",
        "name_fr": "Arrière-pays dravanien",
        "name_ja": "低地ドラヴァニア",
        "name_de": "Dravanisches Hinterland",
        "size_factor": 95,
        "map": 213,
        "aetherytes": [],
        "mobs": [
            {
                "id": 64,
                "name": "Slipkinx steeljoints",
                "name_fr": "Slipkinx joints-d'acier",
                "name_ja": "機兵のスリップキンクス",
                "name_de": "Rutschfix stahlscharnier",
                "rank": 2,
                "npcbase": 4543,
                "mob_index": 1
            },
            {
                "id": 65,
                "name": "Stolas",
                "name_fr": "Stolas",
                "name_ja": "ストラス",
                "name_de": "Stolas",
                "rank": 2,
                "npcbase": 4544,
                "mob_index": 2
            }
        ]
    },
    {
        "id": 400,
        "version": 1,
        "name": "The Churning Mists",
        "name_fr": "L'Écume des cieux de Dravania",
        "name_ja": "ドラヴァニア雲海",
        "name_de": "Wallende Nebel",
        "size_factor": 95,
        "map": 214,
        "aetherytes": [
            {
                "type": 60453,
                "x": 10.8,
                "y": 28.9,
                "name": "Zenith",
                "name_fr": "Zénith",
                "name_ja": "白亜の宮殿",
                "name_de": "Kreidetempel"
            },
            {
                "type": 60453,
                "x": 27.9,
                "y": 34.3,
                "name": "Moghome",
                "name_fr": "Nid-Mog",
                "name_ja": "モグモグホーム",
                "name_de": "Moglingen"
            }
        ],
        "mobs": [
            {
                "id": 69,
                "name": "Bune",
                "name_fr": "Bune",
                "name_ja": "ブネ",
                "name_de": "Bune",
                "rank": 2,
                "npcbase": 4545,
                "mob_index": 1
            },
            {
                "id": 70,
                "name": "Agathos",
                "name_fr": "Agathos",
                "name_ja": "アガトス",
                "name_de": "Agathos",
                "rank": 2,
                "npcbase": 4546,
                "mob_index": 2
            }
        ]
    },
    {
        "id": 612,
        "version": 2,
        "name": "The Fringes",
        "name_fr": "Les Marges",
        "name_ja": "ギラバニア辺境地帯",
        "name_de": "Abanisches Grenzland",
        "size_factor": 100,
        "map": 367,
        "aetherytes": [
            {
                "type": 60453,
                "x": 29.8,
                "y": 26.4,
                "name": "The Peering Stones",
                "name_fr": "Rochers d'aguet",
                "name_ja": "ピーリングストーンズ",
                "name_de": "Die Spähenden Steine"
            },
            {
                "type": 60453,
                "x": 8.9,
                "y": 11.3,
                "name": "Castrum Oriens",
                "name_fr": "Castrum Oriens",
                "name_ja": "カストルム・オリエンス",
                "name_de": "Castrum Oriens"
            }
        ],
        "mobs": [
            {
                "id": 99,
                "name": "Orcus",
                "name_fr": "Orcus",
                "name_ja": "オルクス",
                "name_de": "Orcus",
                "rank": 2,
                "npcbase": 6839,
                "mob_index": 1
            },
            {
                "id": 100,
                "name": "Erle",
                "name_fr": "Erle",
                "name_ja": "アール",
                "name_de": "Erle",
                "rank": 2,
                "npcbase": 6840,
                "mob_index": 2
            }
        ]
    },
    {
        "id": 620,
        "version": 2,
        "name": "The Peaks",
        "name_fr": "Les Pics",
        "name_ja": "ギラバニア山岳地帯",
        "name_de": "Die Zinnen",
        "size_factor": 100,
        "map": 368,
        "aetherytes": [
            {
                "type": 60453,
                "x": 23.7,
                "y": 6.5,
                "name": "Ala Gannha",
                "name_fr": "Ala Gannha",
                "name_ja": "アラガーナ",
                "name_de": "Ala Gannha"
            },
            {
                "type": 60453,
                "x": 16.1,
                "y": 36.4,
                "name": "Ala Ghiri",
                "name_fr": "Ala Ghiri",
                "name_ja": "アラギリ",
                "name_de": "Ala Ghiri"
            }
        ],
        "mobs": [
            {
                "id": 104,
                "name": "Vochstein",
                "name_fr": "Vochstein",
                "name_ja": "バックスタイン",
                "name_de": "Vochstein",
                "rank": 2,
                "npcbase": 6841,
                "mob_index": 1
            },
            {
                "id": 105,
                "name": "Aqrabuamelu",
                "name_fr": "Aqrabuamelu",
                "name_ja": "アクラブアメル",
                "name_de": "Aqrabuamelu",
                "rank": 2,
                "npcbase": 6842,
                "mob_index": 2
            }
        ]
    },
    {
        "id": 621,
        "version": 2,
        "name": "The Lochs",
        "name_fr": "Les Lacs",
        "name_ja": "ギラバニア湖畔地帯",
        "name_de": "Das Fenn",
        "size_factor": 100,
        "map": 369,
        "aetherytes": [
            {
                "type": 60453,
                "x": 8.5,
                "y": 21.1,
                "name": "Porta Praetoria",
                "name_fr": "Porta Praetoria",
                "name_ja": "ポルタ・プレトリア",
                "name_de": "Porta Praetoria"
            },
            {
                "type": 60453,
                "x": 33.8,
                "y": 34.5,
                "name": "The Ala Mhigan Quarter",
                "name_fr": "Faubourg mhigois",
                "name_ja": "アラミガン・クォーター",
                "name_de": "Mhigisches Wohn<SoftHyphen/>viertel"
            }
        ],
        "mobs": [
            {
                "id": 109,
                "name": "Mahisha",
                "name_fr": "Mahisha",
                "name_ja": "マヒシャ",
                "name_de": "Mahisha",
                "rank": 2,
                "npcbase": 6843,
                "mob_index": 1
            },
            {
                "id": 110,
                "name": "Luminare",
                "name_fr": "Luminare",
                "name_ja": "ルミナーレ",
                "name_de": "Luminare",
                "rank": 2,
                "npcbase": 6844,
                "mob_index": 2
            }
        ]
    },
    {
        "id": 613,
        "version": 2,
        "name": "The Ruby Sea",
        "name_fr": "Mer de Rubis",
        "name_ja": "紅玉海",
        "name_de": "Rubinsee",
        "size_factor": 100,
        "map": 371,
        "aetherytes": [
            {
                "type": 60453,
                "x": 28.7,
                "y": 16.3,
                "name": "Tamamizu",
                "name_fr": "Tamamizu",
                "name_ja": "碧のタマミズ",
                "name_de": "Tamamizu"
            },
            {
                "type": 60453,
                "x": 23.3,
                "y": 9.8,
                "name": "Onokoro",
                "name_fr": "Onokoro",
                "name_ja": "オノコロ島",
                "name_de": "Onokoro"
            }
        ],
        "mobs": [
            {
                "id": 84,
                "name": "Funa yurei",
                "name_fr": "Funa yurei",
                "name_ja": "船幽霊",
                "name_de": "Funa yurei",
                "rank": 2,
                "npcbase": 6845,
                "mob_index": 1
            },
            {
                "id": 85,
                "name": "Oni yumemi",
                "name_fr": "Oni yumemi",
                "name_ja": "オニユメミ",
                "name_de": "Oni yumemi",
                "rank": 2,
                "npcbase": 6846,
                "mob_index": 2
            }
        ]
    },
    {
        "id": 614,
        "version": 2,
        "name": "Yanxia",
        "name_fr": "Yanxia",
        "name_ja": "ヤンサ",
        "name_de": "Yanxia",
        "size_factor": 100,
        "map": 354,
        "aetherytes": [
            {
                "type": 60453,
                "x": 30.2,
                "y": 19.7,
                "name": "Namai",
                "name_fr": "Namai",
                "name_ja": "ナマイ村",
                "name_de": "Namai"
            },
            {
                "type": 60453,
                "x": 26.4,
                "y": 13.4,
                "name": "The House of the Fierce",
                "name_fr": "Cercle des Intrépides",
                "name_ja": "烈士庵",
                "name_de": "Klause der Grimmigen"
            }
        ],
        "mobs": [
            {
                "id": 89,
                "name": "Gajasura",
                "name_fr": "Gajasura",
                "name_ja": "ガジャースラ",
                "name_de": "Gajasura",
                "rank": 2,
                "npcbase": 6847,
                "mob_index": 1
            },
            {
                "id": 90,
                "name": "Angada",
                "name_fr": "Angada",
                "name_ja": "アンガダ",
                "name_de": "Angada",
                "rank": 2,
                "npcbase": 6848,
                "mob_index": 2
            }
        ]
    },
    {
        "id": 622,
        "version": 2,
        "name": "The Azim Steppe",
        "name_fr": "Steppe d'Azim",
        "name_ja": "アジムステップ",
        "name_de": "Azim-Steppe",
        "size_factor": 100,
        "map": 372,
        "aetherytes": [
            {
                "type": 60453,
                "x": 32.6,
                "y": 28.3,
                "name": "Reunion",
                "name_fr": "Ralliement",
                "name_ja": "再会の市",
                "name_de": "Reunion"
            },
            {
                "type": 60453,
                "x": 23.1,
                "y": 22.2,
                "name": "The Dawn Throne",
                "name_fr": "Trône de l'Aube",
                "name_ja": "明けの玉座",
                "name_de": "Morgenthron"
            },
            {
                "type": 60453,
                "x": 6.4,
                "y": 23.8,
                "name": "Dhoro Iloh",
                "name_fr": "Dhoro Iloh",
                "name_ja": "ドーロ・イロー",
                "name_de": "Dhoro Iloh"
            }
        ],
        "mobs": [
            {
                "id": 94,
                "name": "Girimekhala",
                "name_fr": "Girimekhala",
                "name_ja": "ギリメカラ",
                "name_de": "Girimekhala",
                "rank": 2,
                "npcbase": 6849,
                "mob_index": 1
            },
            {
                "id": 95,
                "name": "Sum",
                "name_fr": "Sum",
                "name_ja": "ソム",
                "name_de": "Sum",
                "rank": 2,
                "npcbase": 6850,
                "mob_index": 2
            }
        ]
    },
    {
        "id": 813,
        "version": 3,
        "name": "Lakeland",
        "name_fr": "Grand-Lac",
        "name_ja": "レイクランド",
        "name_de": "Seenland",
        "size_factor": 100,
        "map": 491,
        "aetherytes": [
            {
                "type": 60453,
                "x": 36.6,
                "y": 20.9,
                "name": "Fort Jobb",
                "name_fr": "Fort Jobb",
                "name_ja": "ジョッブ砦",
                "name_de": "Jobb-Feste"
            },
            {
                "type": 60453,
                "x": 6.8,
                "y": 16.9,
                "name": "The Ostall Imperative",
                "name_fr": "L'Impératif d'Ostall",
                "name_ja": "オスタル厳命城",
                "name_de": "Ostalls Befehl"
            }
        ],
        "mobs": [
            {
                "id": 114,
                "name": "Nuckelavee",
                "name_fr": "Nuckelavee",
                "name_ja": "ナックラヴィー",
                "name_de": "Nuckelavee",
                "rank": 2,
                "npcbase": 10383,
                "mob_index": 1
            },
            {
                "id": 115,
                "name": "Nariphon",
                "name_fr": "Nariphon",
                "name_ja": "ナリーポン",
                "name_de": "Nariphon",
                "rank": 2,
                "npcbase": 10384,
                "mob_index": 2
            }
        ]
    },
    {
        "id": 814,
        "version": 3,
        "name": "Kholusia",
        "name_fr": "Kholusia",
        "name_ja": "コルシア島",
        "name_de": "Kholusia",
        "size_factor": 100,
        "map": 492,
        "aetherytes": [
            {
                "type": 60453,
                "x": 34.9,
                "y": 27.3,
                "name": "Stilltide",
                "name_fr": "Douceonde",
                "name_ja": "スティルタイド",
                "name_de": "Stillwasser"
            },
            {
                "type": 60453,
                "x": 16.6,
                "y": 29.2,
                "name": "Wright",
                "name_fr": "Cherpant",
                "name_ja": "ライト村",
                "name_de": "Werfting"
            },
            {
                "type": 60453,
                "x": 13.0,
                "y": 9.0,
                "name": "Tomra",
                "name_fr": "Tomra",
                "name_ja": "トメラの村",
                "name_de": "Tomra"
            }
        ],
        "mobs": [
            {
                "id": 119,
                "name": "Li'l murderer",
                "name_fr": "Traître",
                "name_ja": "リルマーダー",
                "name_de": "Kleiner mörder",
                "rank": 2,
                "npcbase": 10420,
                "mob_index": 1
            },
            {
                "id": 120,
                "name": "Huracan",
                "name_fr": "Huracan",
                "name_ja": "フラカン",
                "name_de": "Huracan",
                "rank": 2,
                "npcbase": 10421,
                "mob_index": 2
            }
        ]
    },
    {
        "id": 815,
        "version": 3,
        "name": "Amh Araeng",
        "name_fr": "Amh Araeng",
        "name_ja": "アム・アレーン",
        "name_de": "Amh Araeng",
        "size_factor": 100,
        "map": 493,
        "aetherytes": [
            {
                "type": 60453,
                "x": 26.4,
                "y": 17.0,
                "name": "Mord Souq",
                "name_fr": "Mord Souq",
                "name_ja": "モルド・スーク",
                "name_de": "Mordh Souq"
            },
            {
                "type": 60453,
                "x": 29.5,
                "y": 27.7,
                "name": "The Inn at Journey's Head",
                "name_fr": "Auberge du Grand Départ",
                "name_ja": "旅立ちの宿",
                "name_de": "Ruhstatt vor der Langen Reise"
            },
            {
                "type": 60453,
                "x": 11.3,
                "y": 17.2,
                "name": "Twine",
                "name_fr": "Queues-liées",
                "name_ja": "トゥワイン",
                "name_de": "Pfotenschlag"
            }
        ],
        "mobs": [
            {
                "id": 124,
                "name": "Maliktender",
                "name_fr": "Malikpampa",
                "name_ja": "マリクテンダー",
                "name_de": "Malikkaktor",
                "rank": 2,
                "npcbase": 10356,
                "mob_index": 1
            },
            {
                "id": 125,
                "name": "Sugaar",
                "name_fr": "Sugaar",
                "name_ja": "シュガール",
                "name_de": "Sugaar",
                "rank": 2,
                "npcbase": 10357,
                "mob_index": 2
            }
        ]
    },
    {
        "id": 816,
        "version": 3,
        "name": "Il Mheg",
        "name_fr": "Il Mheg",
        "name_ja": "イル・メグ",
        "name_de": "Il Mheg",
        "size_factor": 100,
        "map": 494,
        "aetherytes": [
            {
                "type": 60453,
                "x": 14.6,
                "y": 31.7,
                "name": "Lydha Lran",
                "name_fr": "Lydha Lran",
                "name_ja": "リダ・ラーン",
                "name_de": "Lydha Lran"
            },
            {
                "type": 60453,
                "x": 20.1,
                "y": 4.3,
                "name": "Pla Enni",
                "name_fr": "Pla Enni",
                "name_ja": "プラ・エンニ茸窟",
                "name_de": "Pla Enni"
            },
            {
                "type": 60453,
                "x": 29.1,
                "y": 7.7,
                "name": "Wolekdorf",
                "name_fr": "Wolekdorf",
                "name_ja": "ヴォレクドルフ",
                "name_de": "Wolekdorf"
            }
        ],
        "mobs": [
            {
                "id": 129,
                "name": "The mudman",
                "name_fr": "Tas de boue",
                "name_ja": "泥人",
                "name_de": "Matschklops",
                "rank": 2,
                "npcbase": 10271,
                "mob_index": 1
            },
            {
                "id": 130,
                "name": "O poorest pauldia",
                "name_fr": "Pauldia",
                "name_ja": "ポールディア",
                "name_de": "Gepeinigter pauldia",
                "rank": 2,
                "npcbase": 10272,
                "mob_index": 2
            }
        ]
    },
    {
        "id": 817,
        "version": 3,
        "name": "The Rak'tika Greatwood",
        "name_fr": "Rak'tika",
        "name_ja": "ラケティカ大森林",
        "name_de": "Der Große Wald Rak'tika",
        "size_factor": 100,
        "map": 495,
        "aetherytes": [
            {
                "type": 60453,
                "x": 19.4,
                "y": 27.4,
                "name": "Slitherbough",
                "name_fr": "Serpentige",
                "name_ja": "スリザーバウ",
                "name_de": "Schlangenzweig"
            },
            {
                "type": 60453,
                "x": 29.1,
                "y": 17.6,
                "name": "Fanow",
                "name_fr": "Fanow",
                "name_ja": "ファノヴの里",
                "name_de": "Fanow"
            }
        ],
        "mobs": [
            {
                "id": 134,
                "name": "Supay",
                "name_fr": "Supay",
                "name_ja": "スペイ",
                "name_de": "Supay",
                "rank": 2,
                "npcbase": 10297,
                "mob_index": 1
            },
            {
                "id": 135,
                "name": "Grassman",
                "name_fr": "Sasquatch arboricole",
                "name_ja": "グラスマン",
                "name_de": "Grasmann",
                "rank": 2,
                "npcbase": 10298,
                "mob_index": 2
            }
        ]
    },
    {
        "id": 818,
        "version": 3,
        "name": "The Tempest",
        "name_fr": "La Tempête",
        "name_ja": "テンペスト",
        "name_de": "Tempest",
        "size_factor": 100,
        "map": 496,
        "aetherytes": [
            {
                "type": 60453,
                "x": 32.7,
                "y": 17.5,
                "name": "The Ondo Cups",
                "name_fr": "Baïne",
                "name_ja": "オンドの潮溜まり",
                "name_de": "Ondo-Becken"
            },
            {
                "type": 60453,
                "x": 18.7,
                "y": 25.9,
                "name": "The Macarenses Angle",
                "name_fr": "Carré macarien",
                "name_ja": "マカレンサス広場",
                "name_de": "Macarenses-Forum"
            }
        ],
        "mobs": [
            {
                "id": 139,
                "name": "Rusalka",
                "name_fr": "Roussalka",
                "name_ja": "ルサルカ",
                "name_de": "Rusalka",
                "rank": 2,
                "npcbase": 10323,
                "mob_index": 1
            },
            {
                "id": 140,
                "name": "Baal",
                "name_fr": "Baal",
                "name_ja": "バール",
                "name_de": "Baal",
                "rank": 2,
                "npcbase": 10324,
                "mob_index": 2
            }
        ]
    },
    {
        "id": 956,
        "version": 4,
        "name": "Labyrinthos",
        "name_fr": "Le Labyrinthos",
        "name_ja": "ラヴィリンソス",
        "name_de": "Labyrinthos",
        "size_factor": 100,
        "map": 695,
        "aetherytes": [
            {
                "type": 60453,
                "x": 30.4,
                "y": 11.9,
                "name": "The Archeion",
                "name_fr": "Archéion",
                "name_ja": "アルケイオン保管院",
                "name_de": "Archeion"
            },
            {
                "type": 60453,
                "x": 21.7,
                "y": 20.5,
                "name": "Sharlayan Hamlet",
                "name_fr": "Petite Sharlayan",
                "name_ja": "リトルシャーレアン",
                "name_de": "Klein-Sharlayan"
            },
            {
                "type": 60453,
                "x": 6.9,
                "y": 27.5,
                "name": "Aporia",
                "name_fr": "L'Aporie",
                "name_ja": "アポリア本部",
                "name_de": "Aporia"
            }
        ],
        "mobs": [
            {
                "id": 174,
                "name": "Hulder",
                "name_fr": "Huldre",
                "name_ja": "フルドラ",
                "name_de": "Hulder",
                "rank": 2,
                "npcbase": 13789,
                "mob_index": 1
            },
            {
                "id": 175,
                "name": "Storsie",
                "name_fr": "Storsie",
                "name_ja": "ストーシー",
                "name_de": "Storsie",
                "rank": 2,
                "npcbase": 13790,
                "mob_index": 2
            }
        ]
    },
    {
        "id": 957,
        "version": 4,
        "name": "Thavnair",
        "name_fr": "Thavnair",
        "name_ja": "サベネア島",
        "name_de": "Thavnair",
        "size_factor": 100,
        "map": 696,
        "aetherytes": [
            {
                "type": 60453,
                "x": 25.4,
                "y": 34.1,
                "name": "Yedlihmad",
                "name_fr": "Yedlihmad",
                "name_ja": "イェドリマン",
                "name_de": "Yedlihmad"
            },
            {
                "type": 60453,
                "x": 11.0,
                "y": 22.2,
                "name": "The Great Work",
                "name_fr": "Le Grand Œuvre",
                "name_ja": "デミールの遺烈郷",
                "name_de": "Daemirs Werk"
            },
            {
                "type": 60453,
                "x": 29.6,
                "y": 16.6,
                "name": "Palaka's Stand",
                "name_fr": "Écoute des Palaka",
                "name_ja": "パーラカの里",
                "name_de": "Palakas Ruh"
            }
        ],
        "mobs": [
            {
                "id": 184,
                "name": "Yilan",
                "name_fr": "Yilan",
                "name_ja": "ユラン",
                "name_de": "Yilan",
                "rank": 2,
                "npcbase": 13759,
                "mob_index": 1
            },
            {
                "id": 185,
                "name": "Sugriva",
                "name_fr": "Sugriva",
                "name_ja": "スグリーヴァ",
                "name_de": "Sugriva",
                "rank": 2,
                "npcbase": 13820,
                "mob_index": 2
            }
        ]
    },
    {
        "id": 958,
        "version": 4,
        "name": "Garlemald",
        "name_fr": "Garlemald",
        "name_ja": "ガレマルド",
        "name_de": "Garlemald",
        "size_factor": 100,
        "map": 697,
        "aetherytes": [
            {
                "type": 60453,
                "x": 13.3,
                "y": 31.1,
                "name": "Camp Broken Glass",
                "name_fr": "Camp Bris-de-glace",
                "name_ja": "キャンプ・ブロークングラス",
                "name_de": "Camp Splitterglas"
            },
            {
                "type": 60453,
                "x": 31.9,
                "y": 17.9,
                "name": "Tertium",
                "name_fr": "Gare de Tertium",
                "name_ja": "テルティウム駅",
                "name_de": "Tertium"
            }
        ],
        "mobs": [
            {
                "id": 194,
                "name": "Minerva",
                "name_fr": "Minerva",
                "name_ja": "ミネルウァ",
                "name_de": "Minerva",
                "rank": 2,
                "npcbase": 13833,
                "mob_index": 1
            },
            {
                "id": 195,
                "name": "Aegeiros",
                "name_fr": "Ægeiros",
                "name_ja": "アイゲイロス",
                "name_de": "Aegeiros",
                "rank": 2,
                "npcbase": 13937,
                "mob_index": 2
            }
        ]
    },
    {
        "id": 959,
        "version": 4,
        "name": "Mare Lamentorum",
        "name_fr": "Mare Lamentorum",
        "name_ja": "嘆きの海",
        "name_de": "Mare Lamentorum",
        "size_factor": 100,
        "map": 698,
        "aetherytes": [
            {
                "type": 60453,
                "x": 10.1,
                "y": 34.5,
                "name": "Sinus Lacrimarum",
                "name_fr": "Sinus Lacrimarum",
                "name_ja": "涙の入江",
                "name_de": "Sinus Lacrimarum"
            },
            {
                "type": 60453,
                "x": 21.5,
                "y": 11.2,
                "name": "Bestways Burrow",
                "name_fr": "Halot de Bestway",
                "name_ja": "ベストウェイ・バロー",
                "name_de": "Bestways Rast"
            }
        ],
        "mobs": [
            {
                "id": 204,
                "name": "Mousse princess",
                "name_fr": "Princesse mousse",
                "name_ja": "ムースプリンセス",
                "name_de": "Mousse-prinzessin",
                "rank": 2,
                "npcbase": 13835,
                "mob_index": 1
            },
            {
                "id": 205,
                "name": "Lunatender queen",
                "name_fr": "Pampa sélénienne reine",
                "name_ja": "ルナテンダー・クイーン",
                "name_de": "Lunatender-königin",
                "rank": 2,
                "npcbase": 13791,
                "mob_index": 2
            }
        ]
    },
    {
        "id": 960,
        "version": 4,
        "name": "Ultima Thule",
        "name_fr": "Ultima Thulé",
        "name_ja": "ウルティマ・トゥーレ",
        "name_de": "Ultima Thule",
        "size_factor": 100,
        "map": 699,
        "aetherytes": [
            {
                "type": 60453,
                "x": 10.6,
                "y": 26.8,
                "name": "Reah Tahra",
                "name_fr": "Reah Tahra",
                "name_ja": "リア・ターラ",
                "name_de": "Reah Tahra"
            },
            {
                "type": 60453,
                "x": 22.7,
                "y": 8.3,
                "name": "Abode of the Ea",
                "name_fr": "Demeure des Éas",
                "name_ja": "イーアの里",
                "name_de": "Domizil der Ea"
            },
            {
                "type": 60453,
                "x": 31.3,
                "y": 28.1,
                "name": "Base Omicron",
                "name_fr": "Base des Omicrons",
                "name_ja": "オミクロンベース",
                "name_de": "Omikron-Basis"
            }
        ],
        "mobs": [
            {
                "id": 224,
                "name": "Arch-eta",
                "name_fr": "Arch-êta",
                "name_ja": "アーチイータ",
                "name_de": "Erz-eta",
                "rank": 2,
                "npcbase": 13760,
                "mob_index": 1
            },
            {
                "id": 225,
                "name": "Fan ail",
                "name_fr": "Fan ail",
                "name_ja": "ファン・アイル",
                "name_de": "Fan ail",
                "rank": 2,
                "npcbase": 13761,
                "mob_index": 2
            }
        ]
    },
    {
        "id": 961,
        "version": 4,
        "name": "Elpis",
        "name_fr": "Elpis",
        "name_ja": "エルピス",
        "name_de": "Elpis",
        "size_factor": 100,
        "map": 700,
        "aetherytes": [
            {
                "type": 60453,
                "x": 24.7,
                "y": 24.0,
                "name": "Anagnorisis",
                "name_fr": "L'Anagnorisis",
                "name_ja": "アナグノリシス天測園",
                "name_de": "Anagnorisis"
            },
            {
                "type": 60453,
                "x": 8.8,
                "y": 32.4,
                "name": "The Twelve Wonders",
                "name_fr": "Les Douze Merveilles",
                "name_ja": "十二節の園",
                "name_de": "Die Zwölf Gärten"
            },
            {
                "type": 60453,
                "x": 10.9,
                "y": 17.1,
                "name": "Poieten Oikos",
                "name_fr": "Poièten Oïkos",
                "name_ja": "ポイエテーン・オイコス",
                "name_de": "Poieten Oikos"
            }
        ],
        "mobs": [
            {
                "id": 214,
                "name": "Petalodus",
                "name_fr": "Petalodus",
                "name_ja": "ペタロドゥス",
                "name_de": "Petalodus",
                "rank": 2,
                "npcbase": 13819,
                "mob_index": 1
            },
            {
                "id": 215,
                "name": "Gurangatch",
                "name_fr": "Gurangatch",
                "name_ja": "グランガチ",
                "name_de": "Gurangatch",
                "rank": 2,
                "npcbase": 13851,
                "mob_index": 2
            }
        ]
    },
    {
        "id": 1187,
        "version": 5,
        "name": "Urqopacha",
        "name_fr": "Urqopacha",
        "name_ja": "オルコ・パチャ",
        "name_de": "Urqopacha",
        "size_factor": 100,
        "map": 857,
        "aetherytes": [
            {
                "type": 60453,
                "x": 28.1,
                "y": 13.2,
                "name": "Wachunpelo",
                "name_fr": "Wachunpelo",
                "name_ja": "ワチュン・ペロ",
                "name_de": "Wachunpelo"
            },
            {
                "type": 60453,
                "x": 30.8,
                "y": 34.2,
                "name": "Worlar's Echo",
                "name_fr": "L'Écho de Worlar",
                "name_ja": "ウォーラーの残響",
                "name_de": "Worlars Echo"
            }
        ],
        "mobs": [
            {
                "id": 234,
                "name": "Queen hawk",
                "name_fr": "Reine des guêpes",
                "name_ja": "クイーンホーク",
                "name_de": "Falkenkönigin",
                "rank": 2,
                "npcbase": 17707,
                "mob_index": 1
            },
            {
                "id": 235,
                "name": "Nechuciho",
                "name_fr": "Nechukiho",
                "name_ja": "ネチュキホ",
                "name_de": "Nechuciho",
                "rank": 2,
                "npcbase": 17708,
                "mob_index": 2
            }
        ]
    },
    {
        "id": 1188,
        "version": 5,
        "name": "Kozama'uka",
        "name_fr": "Kozama'uka",
        "name_ja": "コザマル・カ",
        "name_de": "Kozama'uka",
        "size_factor": 100,
        "map": 858,
        "aetherytes": [
            {
                "type": 60453,
                "x": 18.1,
                "y": 11.9,
                "name": "Ok'hanu",
                "name_fr": "Ok'hanu",
                "name_ja": "オック・ハヌ",
                "name_de": "Ok'hanu"
            },
            {
                "type": 60453,
                "x": 32.3,
                "y": 25.6,
                "name": "Many Fires",
                "name_fr": "Maints-Feux",
                "name_ja": "朋友の灯火",
                "name_de": "Viele Flammen"
            },
            {
                "type": 60453,
                "x": 11.9,
                "y": 27.7,
                "name": "Earthenshire",
                "name_fr": "La Fournée",
                "name_ja": "アースンシャイア",
                "name_de": "Irdehalde"
            }
        ],
        "mobs": [
            {
                "id": 244,
                "name": "The raintriller",
                "name_fr": "Trilleur de pluie",
                "name_ja": "レイントリラー",
                "name_de": "Regentriller",
                "rank": 2,
                "npcbase": 17791,
                "mob_index": 1
            },
            {
                "id": 245,
                "name": "Pkuucha",
                "name_fr": "Pkuucha",
                "name_ja": "プクーチャ",
                "name_de": "Pkuucha",
                "rank": 2,
                "npcbase": 17792,
                "mob_index": 2
            }
        ]
    },
    {
        "id": 1189,
        "version": 5,
        "name": "Yak T'el",
        "name_fr": "Yak T'el",
        "name_ja": "ヤクテル樹海",
        "name_de": "Yak T'el",
        "size_factor": 100,
        "map": 859,
        "aetherytes": [
            {
                "type": 60453,
                "x": 13.5,
                "y": 12.9,
                "name": "Iq Br'aax",
                "name_fr": "Iq Br'aax",
                "name_ja": "イクブラーシャ",
                "name_de": "Iq Br'aax"
            },
            {
                "type": 60453,
                "x": 35.9,
                "y": 32.0,
                "name": "Mamook",
                "name_fr": "Mamook",
                "name_ja": "マムーク",
                "name_de": "Mamook"
            }
        ],
        "mobs": [
            {
                "id": 254,
                "name": "Rrax yity'a",
                "name_fr": "Rrax yity'a",
                "name_ja": "ラシュイチャ",
                "name_de": "Rrax yity'a",
                "rank": 2,
                "npcbase": 16946,
                "mob_index": 1
            },
            {
                "id": 255,
                "name": "Starcrier",
                "name_fr": "Furopluminescent",
                "name_ja": "幻煌鳥",
                "name_de": "Sternschreier",
                "rank": 2,
                "npcbase": 16892,
                "mob_index": 2
            }
        ]
    },
    {
        "id": 1190,
        "version": 5,
        "name": "Shaaloani",
        "name_fr": "Shaaloani",
        "name_ja": "シャーローニ荒野",
        "name_de": "Shaaloani",
        "size_factor": 100,
        "map": 860,
        "aetherytes": [
            {
                "type": 60453,
                "x": 29.1,
                "y": 30.8,
                "name": "Hhusatahwi",
                "name_fr": "Hhusatahwi",
                "name_ja": "フーサタイ宿場町",
                "name_de": "Hhusatahwi"
            },
            {
                "type": 60453,
                "x": 27.7,
                "y": 10.1,
                "name": "Mehwahhetsoan",
                "name_fr": "Mehwahhetsoan",
                "name_ja": "メワヘイゾーン",
                "name_de": "Mehwahhetsoan"
            },
            {
                "type": 60453,
                "x": 15.7,
                "y": 19.2,
                "name": "Sheshenewezi Springs",
                "name_fr": "Sources de Sheshenewezi",
                "name_ja": "シェシェネ青燐泉",
                "name_de": "Sheshenewezi-Quellen"
            }
        ],
        "mobs": [
            {
                "id": 264,
                "name": "Yehehetoaua'pyo",
                "name_fr": "Yehehetoaua'pyo",
                "name_ja": "エヘヘトーワポ",
                "name_de": "Yehehetoaua'pyo",
                "rank": 2,
                "npcbase": 17371,
                "mob_index": 1
            },
            {
                "id": 265,
                "name": "Keheniheyamewi",
                "name_fr": "Keheniheyamewi",
                "name_ja": "ケヘニヘヤメウィ",
                "name_de": "Keheniheyamewi",
                "rank": 2,
                "npcbase": 17372,
                "mob_index": 2
            }
        ]
    },
    {
        "id": 1191,
        "version": 5,
        "name": "Heritage Found",
        "name_fr": "L'Hoirie recouvrée",
        "name_ja": "ヘリテージファウンド",
        "name_de": "Ewiges Erbe",
        "size_factor": 100,
        "map": 861,
        "aetherytes": [
            {
                "type": 60453,
                "x": 31.8,
                "y": 25.6,
                "name": "Yyasulani Station",
                "name_fr": "Gare de Yyasulani",
                "name_ja": "ヤースラニ駅",
                "name_de": "Bahnhof Yyasulani"
            },
            {
                "type": 60453,
                "x": 17.1,
                "y": 23.9,
                "name": "Electrope Strike",
                "name_fr": "Mines d'Électrope",
                "name_ja": "エレクトロープ採石場",
                "name_de": "Elektrob-Bruch"
            },
            {
                "type": 60453,
                "x": 17.1,
                "y": 9.8,
                "name": "The Outskirts",
                "name_fr": "Les Faubourgs",
                "name_ja": "アウトスカーツ",
                "name_de": "Außenbezirke"
            }
        ],
        "mobs": [
            {
                "id": 274,
                "name": "Heshuala",
                "name_fr": "Heshuala",
                "name_ja": "ヘシュワラ",
                "name_de": "Heshuala",
                "rank": 2,
                "npcbase": 16750,
                "mob_index": 1
            },
            {
                "id": 275,
                "name": "Urna variabilis",
                "name_fr": "Pod variant",
                "name_ja": "ヴァリアポッド",
                "name_de": "Urna variabilis",
                "rank": 2,
                "npcbase": 16751,
                "mob_index": 2
            }
        ]
    },
    {
        "id": 1192,
        "version": 5,
        "name": "Living Memory",
        "name_fr": "La Mémoire vivante",
        "name_ja": "リビング・メモリー",
        "name_de": "Lebende Erinnerung",
        "size_factor": 100,
        "map": 862,
        "aetherytes": [
            {
                "type": 60453,
                "x": 21.5,
                "y": 37.5,
                "name": "Leynode Mnemo",
                "name_fr": "Nœud tellurique mnémo",
                "name_ja": "レイノード・メモリス",
                "name_de": "Leyknoten Mnemo"
            },
            {
                "type": 60453,
                "x": 34.7,
                "y": 15.8,
                "name": "Leynode Pyro",
                "name_fr": "Nœud tellurique pyro",
                "name_ja": "レイノード・ファイア",
                "name_de": "Leyknoten Pyro"
            },
            {
                "type": 60453,
                "x": 16.4,
                "y": 13.6,
                "name": "Leynode Aero",
                "name_fr": "Nœud tellurique aéro",
                "name_ja": "レイノード・ウィンド",
                "name_de": "Leyknoten Aero"
            }
        ],
        "mobs": [
            {
                "id": 284,
                "name": "Sally the sweeper",
                "name_fr": "Sally la balayeuse",
                "name_ja": "サリー・ザ・スイーパー",
                "name_de": "Sally die fegerin",
                "rank": 2,
                "npcbase": 17301,
                "mob_index": 1
            },
            {
                "id": 285,
                "name": "Cat's eye",
                "name_fr": "Œil-de-chat",
                "name_ja": "キャッツアイ",
                "name_de": "Katzenauge",
                "rank": 2,
                "npcbase": 17302,
                "mob_index": 2
            }
        ]
    }
]